lib/__init__.py
lib/console_handler.py
lib/constants/__init__.py
lib/constants/constants.py
lib/constants/serializer_types.py
lib/fabric/__init__.py
lib/fabric/fabric.py
lib/parsers/__init__.py
lib/parsers/json_parser.py
lib/parsers/parser.py
lib/parsers/serializer_core.py
lib/parsers/toml_parser.py
lib/parsers/yaml_parser.py
lib/util/__init__.py
lib/util/serializer_core.py
tests/__init__.py
tests/test_data.py
tests/test_main.py
serialization_utility-1.0.dist-info/METADATA
serialization_utility-1.0.dist-info/WHEEL
serialization_utility-1.0.dist-info/top_level.txt
serialization_utility-1.0.dist-info/RECORD
